<annotation>
	<folder></folder>
	<filename>brightnessquandoi105_jpg.rf.2b2b1f76545af5bff6f68ec4efbac688.jpg</filename>
	<path>brightnessquandoi105_jpg.rf.2b2b1f76545af5bff6f68ec4efbac688.jpg</path>
	<source>
		<database>roboflow.ai</database>
	</source>
	<size>
		<width>800</width>
		<height>530</height>
		<depth>3</depth>
	</size>
	<segmented>0</segmented>
	<object>
		<name>License_Plate</name>
		<pose>Unspecified</pose>
		<truncated>0</truncated>
		<difficult>0</difficult>
		<occluded>0</occluded>
		<bndbox>
			<xmin>274</xmin>
			<xmax>299</xmax>
			<ymin>445</ymin>
			<ymax>472</ymax>
		</bndbox>
	</object>
</annotation>
