<annotation>
	<folder></folder>
	<filename>CarLongPlateGen1245_jpg.rf.380d14f52ec1afa62b830e2ca33974ec.jpg</filename>
	<path>CarLongPlateGen1245_jpg.rf.380d14f52ec1afa62b830e2ca33974ec.jpg</path>
	<source>
		<database>roboflow.ai</database>
	</source>
	<size>
		<width>472</width>
		<height>303</height>
		<depth>3</depth>
	</size>
	<segmented>0</segmented>
	<object>
		<name>License_Plate</name>
		<pose>Unspecified</pose>
		<truncated>0</truncated>
		<difficult>0</difficult>
		<occluded>0</occluded>
		<bndbox>
			<xmin>185</xmin>
			<xmax>288</xmax>
			<ymin>102</ymin>
			<ymax>139</ymax>
		</bndbox>
	</object>
</annotation>
