<annotation>
	<folder></folder>
	<filename>CarLongPlateGen3076_jpg.rf.d20c48bfacb8895c06584682fb065652.jpg</filename>
	<path>CarLongPlateGen3076_jpg.rf.d20c48bfacb8895c06584682fb065652.jpg</path>
	<source>
		<database>roboflow.ai</database>
	</source>
	<size>
		<width>472</width>
		<height>303</height>
		<depth>3</depth>
	</size>
	<segmented>0</segmented>
	<object>
		<name>License_Plate</name>
		<pose>Unspecified</pose>
		<truncated>0</truncated>
		<difficult>0</difficult>
		<occluded>0</occluded>
		<bndbox>
			<xmin>179</xmin>
			<xmax>283</xmax>
			<ymin>226</ymin>
			<ymax>283</ymax>
		</bndbox>
	</object>
</annotation>
