<annotation>
	<folder></folder>
	<filename>Cars351_png_jpg.rf.ba91bc44799765a08e23c3f8a735f313.jpg</filename>
	<path>Cars351_png_jpg.rf.ba91bc44799765a08e23c3f8a735f313.jpg</path>
	<source>
		<database>roboflow.ai</database>
	</source>
	<size>
		<width>400</width>
		<height>225</height>
		<depth>3</depth>
	</size>
	<segmented>0</segmented>
	<object>
		<name>License_Plate</name>
		<pose>Unspecified</pose>
		<truncated>0</truncated>
		<difficult>0</difficult>
		<occluded>0</occluded>
		<bndbox>
			<xmin>249</xmin>
			<xmax>368</xmax>
			<ymin>48</ymin>
			<ymax>129</ymax>
		</bndbox>
	</object>
</annotation>
